OmMongo-1.1.5.dist-info/DESCRIPTION.rst
OmMongo-1.1.5.dist-info/METADATA
OmMongo-1.1.5.dist-info/RECORD
OmMongo-1.1.5.dist-info/WHEEL
OmMongo-1.1.5.dist-info/metadata.json
OmMongo-1.1.5.dist-info/top_level.txt
ommongo/__init__.py
ommongo/document.py
ommongo/exceptions.py
ommongo/ops.py
ommongo/py3compat.py
ommongo/query.py
ommongo/query_expression.py
ommongo/session.py
ommongo/update_expression.py
ommongo/util.py
ommongo/fields/__init__.py
ommongo/fields/base.py
ommongo/fields/document_field.py
ommongo/fields/fields.py
ommongo/fields/mapping.py
ommongo/fields/ref.py
ommongo/fields/sequence.py
