Metadata-Version: 2.0
Name: OmMongo
Version: 1.1.5
Summary: Document-Object Mapper/Toolkit for Mongo Databases
Home-page: https://github.com/bapakode/ommongo
Author: Bapakode Open Source
Author-email: opensource@bapakode.com
License: MIT
Platform: UNKNOWN
Classifier: Development Status :: 3 - Alpha
Classifier: Intended Audience :: Developers
Classifier: License :: OSI Approved :: MIT License
Classifier: Operating System :: OS Independent
Classifier: Programming Language :: Python
Classifier: Topic :: Database
Classifier: Topic :: Software Development :: Libraries :: Python Modules
Requires-Dist: pymongo
